README.md
setup.py
tinysql/__init__.py
tinysql.egg-info/PKG-INFO
tinysql.egg-info/SOURCES.txt
tinysql.egg-info/dependency_links.txt
tinysql.egg-info/top_level.txt