Metadata-Version: 2.1
Name: tinysql
Version: 0.0.1
Summary: tinysql
Home-page: https://gitlab.com/17radix
Author: 17radix
Author-email: 17radix@gmail.com
License: UNKNOWN
Platform: UNKNOWN
Classifier: Programming Language :: Python :: 3
Classifier: License :: OSI Approved :: MIT License
Classifier: Operating System :: OS Independent
